{
    "version": "https://jsonfeed.org/version/1",
    "title": "IP topics",
    "description": "",
    "home_page_url": "https://iptopics.com",
    "feed_url": "https://iptopics.com/feed.json",
    "user_comment": "",
    "icon": "https://iptopics.com/media/website/iptopics-logo.png",
    "author": {
        "name": "Vimana Grioni"
    },
    "items": [
        {
            "id": "https://iptopics.com/fortnite-cheat-distrugge-il-fair-play-mondiale-e-epic-games-cita-in-giudizio-i-creatori-di-vanta-cheats.html",
            "url": "https://iptopics.com/fortnite-cheat-distrugge-il-fair-play-mondiale-e-epic-games-cita-in-giudizio-i-creatori-di-vanta-cheats.html",
            "title": "Fortnite cheat distrugge il fair play mondiale e Epic Games cita in giudizio i creatori di Vanta Cheats",
            "summary": "Epic Games ha intentato una causa esplosiva contro sviluppatori e rivenditori di&hellip;",
            "image": "https://iptopics.com/media/posts/53/Fortnite-Vanta-cheat.jpg",
            "author": {
                "name": "Vimana Grioni"
            },
            "tags": [
                   "videogames",
                   "copyright"
            ],
            "date_published": "2025-06-19T21:37:20+02:00",
            "date_modified": "2025-06-21T09:29:53+02:00"
        },
        {
            "id": "https://iptopics.com/quando-lia-non-obbedisce-inizia-a-somigliarci.html",
            "url": "https://iptopics.com/quando-lia-non-obbedisce-inizia-a-somigliarci.html",
            "title": "Quando l’IA non obbedisce, inizia a somigliarci",
            "summary": "Ti sei mai chiesto come reagirebbe un’intelligenza artificiale se scoprisse che sta&hellip;",
            "image": "https://iptopics.com/media/posts/52/Il-giorno-in-cui-la-macchina-ha-imparato-il-ricatto.jpg",
            "author": {
                "name": "Vimana Grioni"
            },
            "tags": [
                   "pubblicazioni",
                   "notizie brevi",
                   "intelligenza artificiale"
            ],
            "date_published": "2025-06-16T09:36:02+02:00",
            "date_modified": "2025-06-16T14:16:27+02:00"
        },
        {
            "id": "https://iptopics.com/il-confine-tra-benchmark-e-plagio-nel-caso-baby-bellies-contro-aldi.html",
            "url": "https://iptopics.com/il-confine-tra-benchmark-e-plagio-nel-caso-baby-bellies-contro-aldi.html",
            "title": "Il confine tra benchmark e plagio nel caso Baby Bellies contro Aldi",
            "summary": "Una decisione della Corte Federale australiana sancisce che l’uso di benchmark grafici&hellip;",
            "image": "https://iptopics.com/media/posts/51/Little-Bellies-sfida-Aldi.jpg",
            "author": {
                "name": "Vimana Grioni"
            },
            "tags": [
                   "disegni e modelli",
                   "diritto d&#x27;autore",
                   "copyright"
            ],
            "date_published": "2025-06-10T17:53:57+02:00",
            "date_modified": "2025-06-11T07:14:50+02:00"
        },
        {
            "id": "https://iptopics.com/mauritius-aderisce-al-protocollo-di-harare.html",
            "url": "https://iptopics.com/mauritius-aderisce-al-protocollo-di-harare.html",
            "title": "Mauritius aderisce al Protocollo di Harare",
            "summary": "La Repubblica di Mauritius diventerà il 21° membro del Protocollo di Harare,&hellip;",
            "author": {
                "name": "Vimana Grioni"
            },
            "tags": [
                   "notizie brevi"
            ],
            "date_published": "2025-06-08T22:25:56+02:00",
            "date_modified": "2025-06-08T22:31:04+02:00"
        },
        {
            "id": "https://iptopics.com/napster-segnalato-per-copyright-ma-agcom-decide-per-larchiviazione.html",
            "url": "https://iptopics.com/napster-segnalato-per-copyright-ma-agcom-decide-per-larchiviazione.html",
            "title": "Napster segnalato per copyright ma AGCOM decide per l’archiviazione",
            "summary": "SIAE denuncia presunte violazioni massive del diritto d’autore, ma per AGCOM il&hellip;",
            "image": "https://iptopics.com/media/posts/42/Napster-AGCOM-SIAE.jpg",
            "author": {
                "name": "Vimana Grioni"
            },
            "tags": [
                   "musica",
                   "diritto d&#x27;autore"
            ],
            "date_published": "2025-06-06T11:40:07+02:00",
            "date_modified": "2025-06-08T09:52:46+02:00"
        },
        {
            "id": "https://iptopics.com/il-brevetto-che-minaccia-bitcoin.html",
            "url": "https://iptopics.com/il-brevetto-che-minaccia-bitcoin.html",
            "title": "Il brevetto che minaccia Bitcoin",
            "summary": "Una controversa causa negli Stati Uniti rimette in discussione la neutralità tecnologica&hellip;",
            "image": "https://iptopics.com/media/posts/41/Il-brevetto-che-minaccia-Bitcoin.jpg",
            "author": {
                "name": "Vimana Grioni"
            },
            "tags": [
                   "nuove tecnologie",
                   "brevetti",
                   "blockchain"
            ],
            "date_published": "2025-06-05T00:15:39+02:00",
            "date_modified": "2025-06-05T22:44:39+02:00"
        },
        {
            "id": "https://iptopics.com/dainese-e-alpinestars-davanti-allupc-di-milano-per-due-brevetti-europei.html",
            "url": "https://iptopics.com/dainese-e-alpinestars-davanti-allupc-di-milano-per-due-brevetti-europei.html",
            "title": "Dainese e Alpinestars davanti all’UPC di Milano per due brevetti europei",
            "summary": "La sospensione del giudizio su un solo brevetto, chiesta da entrambe le&hellip;",
            "image": "https://iptopics.com/media/posts/40/Dainese-e-Alpinestars-davanti-all-UPC.jpg",
            "author": {
                "name": "Vimana Grioni"
            },
            "tags": [
                   "brevetti",
                   "UPC"
            ],
            "date_published": "2025-06-02T23:42:26+02:00",
            "date_modified": "2025-06-05T22:45:04+02:00"
        },
        {
            "id": "https://iptopics.com/la-deregulation-delle-ia-non-e-innovazione-e-saccheggio-autorizzato.html",
            "url": "https://iptopics.com/la-deregulation-delle-ia-non-e-innovazione-e-saccheggio-autorizzato.html",
            "title": "La deregulation delle IA non è innovazione, è saccheggio autorizzato.",
            "summary": "Se il consenso del titolare di copyright rende “non plausibile” un modello&hellip;",
            "image": "https://iptopics.com/media/posts/39/steve-johnson-VVxQEpum11g-unsplash.jpg",
            "author": {
                "name": "Vimana Grioni"
            },
            "tags": [
                   "intelligenza artificiale",
                   "copyright"
            ],
            "date_published": "2025-05-29T00:39:55+02:00",
            "date_modified": "2025-05-29T01:06:15+02:00"
        },
        {
            "id": "https://iptopics.com/in-bilico-il-futuro-della-normativa-ue-sui-brevetti-standard-essenziali.html",
            "url": "https://iptopics.com/in-bilico-il-futuro-della-normativa-ue-sui-brevetti-standard-essenziali.html",
            "title": "In bilico il futuro della normativa UE sui brevetti standard essenziali",
            "summary": "Lo stop della Commissione europea alla proposta sui SEP solleva critiche e&hellip;",
            "image": "https://iptopics.com/media/posts/29/SEP-EU.jpg",
            "author": {
                "name": "Vimana Grioni"
            },
            "tags": [
                   "brevetti",
                   "SEP"
            ],
            "date_published": "2025-05-23T16:46:21+02:00",
            "date_modified": "2025-05-23T16:46:21+02:00"
        },
        {
            "id": "https://iptopics.com/gta-6-le-tecnologie-brevettate-che-rivoluzionano-gli-open-world.html",
            "url": "https://iptopics.com/gta-6-le-tecnologie-brevettate-che-rivoluzionano-gli-open-world.html",
            "title": "GTA 6: le tecnologie brevettate che rivoluzionano gli open world",
            "summary": "I dieci brevetti di Rockstar Games svelano un progetto ambizioso: rendere GTA&hellip;",
            "image": "https://iptopics.com/media/posts/28/GTA6-brevetti.jpg",
            "author": {
                "name": "Vimana Grioni"
            },
            "tags": [
                   "videogames",
                   "brevetti"
            ],
            "date_published": "2025-05-23T16:29:04+02:00",
            "date_modified": "2025-05-23T16:46:40+02:00"
        }
    ]
}
